README.md
setup.py
bin/streamline
streamline/__init__.py
streamline/cli.py
streamline/consumers.py
streamline/core.py
streamline/entries.py
streamline/executors.py
streamline/extractor.py
streamline/generators.py
streamline/streamers.py
streamline/utils.py
streamline.egg-info/PKG-INFO
streamline.egg-info/SOURCES.txt
streamline.egg-info/dependency_links.txt
streamline.egg-info/requires.txt
streamline.egg-info/top_level.txt