Metadata-Version: 2.1
Name: streamline
Version: 1.1.0
Summary: CLI tool for doing async tasks and transformations
Home-page: https://github.com/jdotpy/streamline
Author: KJ
Author-email: jdotpy@users.noreply.github.com
License: UNKNOWN
Download-URL: https://github.com/jdotpy/streamline/tarball/master
Keywords: tools
Platform: UNKNOWN
Classifier: Programming Language :: Python :: 3
